vcompy/Compiler.py
vcompy/Media.py
vcompy/Overlay.py
vcompy/Text.py
vcompy/Video.py
vcompy/__init__.py
vcompy/version.py
vcompy-0.1.0.dist-info/LICENSE
vcompy-0.1.0.dist-info/METADATA
vcompy-0.1.0.dist-info/WHEEL
vcompy-0.1.0.dist-info/top_level.txt
vcompy-0.1.0.dist-info/RECORD
