Metadata-Version: 2.1
Name: vcompy
Version: 0.1.0
Summary: Video compiler
Home-page: https://github.com/dot-six/vcompy
Author: Hanz <hanz@godot.id>
License: MIT License
Keywords: video editing ffmpeg
License-File: LICENSE
Requires-Dist: Pillow (==9.3.0)
Requires-Dist: imageio (==2.23.0)
Requires-Dist: imageio[pyav]
Requires-Dist: numpy (==1.24.0)
